mbrs/__init__.py
mbrs/args.py
mbrs/args_test.py
mbrs/conftest.py
mbrs/functional.py
mbrs/functional_test.py
mbrs/registry.py
mbrs/registry_test.py
mbrs/timer.py
mbrs/timer_test.py
mbrs/utils.py
mbrs/utils_test.py
mbrs/cli/decode.py
mbrs/cli/generate.py
mbrs/cli/score.py
mbrs/decoders/__init__.py
mbrs/decoders/aggregate_mbr.py
mbrs/decoders/aggregate_mbr_test.py
mbrs/decoders/base.py
mbrs/decoders/centroid_mbr.py
mbrs/decoders/centroid_mbr_test.py
mbrs/decoders/mbr.py
mbrs/decoders/mbr_test.py
mbrs/decoders/probabilistic_mbr.py
mbrs/decoders/probabilistic_mbr_test.py
mbrs/decoders/pruning_mbr.py
mbrs/decoders/pruning_mbr_test.py
mbrs/decoders/rerank.py
mbrs/decoders/rerank_test.py
mbrs/metrics/__init__.py
mbrs/metrics/base.py
mbrs/metrics/bertscore.py
mbrs/metrics/bertscore_test.py
mbrs/metrics/bleu.py
mbrs/metrics/bleu_test.py
mbrs/metrics/bleurt.py
mbrs/metrics/bleurt_test.py
mbrs/metrics/chrf.py
mbrs/metrics/chrf_test.py
mbrs/metrics/comet.py
mbrs/metrics/comet_test.py
mbrs/metrics/cometkiwi.py
mbrs/metrics/cometkiwi_test.py
mbrs/metrics/metricx.py
mbrs/metrics/metricx_test.py
mbrs/metrics/ter.py
mbrs/metrics/ter_test.py
mbrs/metrics/xcomet.py
mbrs/metrics/xcomet_test.py
mbrs/modules/__init__.py
mbrs/modules/als.py
mbrs/modules/als_test.py
mbrs/modules/kmeans.py
mbrs/modules/kmeans_test.py
mbrs/selectors/__init__.py
mbrs/selectors/base.py
mbrs/selectors/diverse.py
mbrs/selectors/diverse_test.py
mbrs/selectors/nbest.py
mbrs/selectors/nbest_test.py
mbrs/tests/plugins/__init__.py
mbrs/tests/plugins/my_bleu.py
mbrs-0.1.7.dist-info/METADATA
mbrs-0.1.7.dist-info/WHEEL
mbrs-0.1.7.dist-info/entry_points.txt
mbrs-0.1.7.dist-info/licenses/LICENSE
mbrs-0.1.7.dist-info/RECORD
