Metadata-Version: 2.4
Name: mbrs
Version: 0.1.7
Summary: A library for minimum Bayes risk (MBR) decoding.
Author-email: Hiroyuki Deguchi <deguchi.hiroyuki.db0@is.naist.jp>
License-File: LICENSE
Requires-Python: >=3.10
Requires-Dist: bert-score>=0.3.13
Requires-Dist: bleurt-pytorch>=0.0.1
Requires-Dist: fastchrf>=0.1.0
Requires-Dist: numpy>=1.26.4
Requires-Dist: sacrebleu[ja]>=2.5.0
Requires-Dist: simple-parsing>=0.1.7
Requires-Dist: tabulate>=0.9.0
Requires-Dist: torch>=2.5.1
Requires-Dist: tqdm>=4.67.1
Requires-Dist: unbabel-comet>=2.2.6
